{
  "format_version": "1.8.0",
  "animations": {
    "animation.kci_shield.thirdperson_main_hand": {
      "loop": true,
      "bones": {
        "geyser_custom_x": {
          "rotation": [
            -0,
            180,
            0
          ],
          "position": [
            -3,
            -1.5,
            6
          ],
          "scale": [
            1.25,
            1.25,
            1.25
          ]
        },
        "geyser_custom_y": {
          "rotation": [
            0,
            90,
            0
          ]
        },
        "geyser_custom_z": {
          "rotation": [
            0,
            0,
            0
          ]
        },
        "geyser_custom": {
          "rotation": [
            90,
            0,
            0
          ],
          "position": [
            0,
            13,
            -3
          ]
        }
      }
    },
    "animation.kci_shield.thirdperson_off_hand": {
      "loop": true,
      "bones": {
        "geyser_custom_x": {
          "rotation": [
            0,
            180,
            0
          ],
          "position": [
            3,
            -2,
            4
          ],
          "scale": [
            1.25,
            1.25,
            1.25
          ]
        },
        "geyser_custom_y": {
          "rotation": [
            0,
            90,
            0
          ]
        },
        "geyser_custom_z": {
          "rotation": [
            0,
            0,
            0
          ]
        },
        "geyser_custom": {
          "rotation": [
            90,
            0,
            0
          ],
          "position": [
            0,
            13,
            -3
          ]
        }
      }
    },
    "animation.kci_shield.head": {
      "loop": true,
      "bones": {
        "geyser_custom_x": {
          "scale": 0.625
        },
        "geyser_custom": {
          "position": [
            0,
            19.9,
            0
          ]
        }
      }
    },
    "animation.kci_shield.firstperson_main_hand": {
      "loop": true,
      "bones": {
        "geyser_custom": {
          "rotation": [
            90,
            60,
            -40
          ],
          "position": [
            4,
            10,
            4
          ]
        },
        "geyser_custom_x": {
          "position": [
            2,
            -5,
            -0
          ],
          "rotation": [
            5,
            0,
            0
          ],
          "scale": [
            1.35,
            1.35,
            1.35
          ]
        },
        "geyser_custom_y": {
          "rotation": [
            0,
            -0,
            0
          ]
        },
        "geyser_custom_z": {
          "rotation": [
            0,
            0,
            -5
          ]
        }
      }
    },
    "animation.kci_shield.firstperson_off_hand": {
      "loop": true,
      "bones": {
        "geyser_custom": {
          "rotation": [
            160,
            60,
            -40
          ],
          "position": [
            -14,
            10,
            4
          ],
          "scale": 1.5
        },
        "geyser_custom_x": {
          "position": [
            -1.5,
            -5,
            -0
          ],
          "rotation": [
            -5,
            0,
            0
          ],
          "scale": [
            1.35,
            1.35,
            1.35
          ]
        },
        "geyser_custom_y": {
          "rotation": [
            0,
            -0,
            0
          ]
        },
        "geyser_custom_z": {
          "rotation": [
            0,
            0,
            -5
          ]
        }
      }
    }
  }
}
